octokit/__init__.py
octokit/auth.py
octokit/client.py
octokit/errors.py
octokit/settings.py
octokit/version.py
octokit.py-0.1.1.dist-info/DESCRIPTION.rst
octokit.py-0.1.1.dist-info/METADATA
octokit.py-0.1.1.dist-info/RECORD
octokit.py-0.1.1.dist-info/WHEEL
octokit.py-0.1.1.dist-info/metadata.json
octokit.py-0.1.1.dist-info/top_level.txt
