Metadata-Version: 2.0
Name: octokit.py
Version: 0.1.1
Summary: Python toolkit for GitHub API
Home-page: http://github.com/irqed/octokit.py
Author: Alexander Shchepetilnikov
Author-email: a@irqed.io
License: The MIT License (MIT)
Requires-Dist: slumber (==0.6.0)
